LAB3/halfAdder.v
module halfAdder (
   input  A,B,
   output S, Cout
);
xor(S,A,B);
and(Cout,A,B);

endmodule

LAB3/fullAdder.v
module fullAdder (
    input A, B, Cin,        // Girişler
    output S, Cout          // Çıkışlar
);

    wire AxB, AnB, AnB1, AnB2;  // Ara sinyaller

    // İlk Half Adder (A + B)
    halfAdder h0 (
        .A(A),
        .B(B),
        .S(AxB),
        .Cout(AnB2)
    );

    // İkinci Half Adder (AxB + Cin)
    halfAdder h1 (
        .A(AxB),
        .B(Cin),
        .S(S),
        .Cout(AnB1)
    );

    // Taşıma çıkışı
    or(Cout, AnB1, AnB2);  // Taşıma çıkışı
endmodule

LAB3/bit3adder.v
module bit3adder(
   input [2:0] A,
   input [2:0] B,
   output [3:0] Sum
);

wire [2:0] Carry3;

halfAdder h1(.A(A[0]), .B(B[0]), .S(Sum[0]), .Cout(Carry3[0]));
fullAdder f1(.A(A[1]), .B(B[1]), .Cin(Carry3[0]), .S(Sum[1]), .Cout(Carry3[1]));
fullAdder f2(.A(A[2]), .B(B[2]), .Cin(Carry3[1]), .S(Sum[2]), .Cout(Sum[3]));



endmodule

LAB3/bit3adderTB.v
module bit3adderTB();
reg [2:0] A;
reg [2:0] B;
wire [3:0] Sum;

bit3adder uut (
    .A(A),
    .B(B),
    .Sum(Sum)
);

initial begin
    $dumpfile("bit3adder.vcd");
    $dumpvars;
    A = 3'b000; B = 3'b000; #10;
    A = 3'b000; B = 3'b001; #10;
    A = 3'b001; B = 3'b001; #10;
    A = 3'b010; B = 3'b010; #10;
    A = 3'b010; B = 3'b011; #10;
    A = 3'b110; B = 3'b010; #10;
    A = 3'b101; B = 3'b100; #10;
    A = 3'b111; B = 3'b100; #10;
    A = 3'b111; B = 3'b110; #10;
    A = 3'b111; B = 3'b111; #10;
    $finish;
end

endmodule

LAB3/bit3adder.vcd
$date
	Mon Feb  3 20:24:25 2025
$end
$version
	Icarus Verilog
$end
$timescale
	1s
$end
$scope module bit3adderTB $end
$var wire 4 ! Sum [3:0] $end
$var reg 3 " A [2:0] $end
$var reg 3 # B [2:0] $end
$scope module uut $end
$var wire 3 $ A [2:0] $end
$var wire 3 % B [2:0] $end
$var wire 4 & Sum [3:0] $end
$var wire 3 ' Carry3 [2:0] $end
$scope module f1 $end
$var wire 1 ( A $end
$var wire 1 ) B $end
$var wire 1 * Cin $end
$var wire 1 + Cout $end
$var wire 1 , S $end
$var wire 1 - AxB $end
$var wire 1 . AnB2 $end
$var wire 1 / AnB1 $end
$scope module h0 $end
$var wire 1 ( A $end
$var wire 1 ) B $end
$var wire 1 . Cout $end
$var wire 1 - S $end
$upscope $end
$scope module h1 $end
$var wire 1 ( A $end
$var wire 1 * B $end
$var wire 1 / Cout $end
$var wire 1 , S $end
$upscope $end
$upscope $end
$scope module f2 $end
$var wire 1 0 A $end
$var wire 1 1 B $end
$var wire 1 2 Cin $end
$var wire 1 3 Cout $end
$var wire 1 4 S $end
$var wire 1 5 AxB $end
$var wire 1 6 AnB2 $end
$var wire 1 7 AnB1 $end
$scope module h0 $end
$var wire 1 0 A $end
$var wire 1 1 B $end
$var wire 1 6 Cout $end
$var wire 1 5 S $end
$upscope $end
$scope module h1 $end
$var wire 1 0 A $end
$var wire 1 2 B $end
$var wire 1 7 Cout $end
$var wire 1 4 S $end
$upscope $end
$upscope $end
$scope module h1 $end
$var wire 1 8 A $end
$var wire 1 9 B $end
$var wire 1 : Cout $end
$var wire 1 ; S $end
$upscope $end
$upscope $end
$upscope $end
$enddefinitions $end
$comment Show the parameter values. $end
$dumpall
$end
#0
$dumpvars
0;
0:
09
08
07
06
05
04
03
02
01
00
0/
0.
0-
0,
0+
0*
0)
0(
bz00 '
b0 &
b0 %
b0 $
b0 #
b0 "
b0 !
$end
#10
b1 !
b1 &
1;
19
b1 #
b1 %
#20
1,
1*
b10 !
b10 &
0;
bz01 '
1:
18
b1 "
b1 $
#30
14
12
0*
1+
bz10 '
0:
1.
b110 !
b110 &
1,
0/
09
1)
08
1(
b10 #
b10 %
b10 "
b10 $
#40
b111 !
b111 &
1;
19
b11 #
b11 %
#50
13
0;
15
b1010 !
b1010 &
04
17
09
10
b10 #
b10 %
b110 "
b110 $
#60
14
07
02
bz00 '
0+
05
16
1;
0.
b1101 !
b1101 &
0,
0)
11
18
0(
b100 #
b100 %
b101 "
b101 $
#70
1-
b1111 !
b1111 &
1,
1(
b111 "
b111 $
#80
b1011 !
b1011 &
04
17
12
bz10 '
1+
0-
1.
1)
b110 #
b110 %
#90
0,
1/
1*
b1000 !
b1000 &
0;
bz11 '
1:
19
b111 #
b111 %
